gsam_utils.cpython-310-x86_64-linux-gnu.so
gsam_utils-0.2.1.dist-info/METADATA
gsam_utils-0.2.1.dist-info/WHEEL
gsam_utils-0.2.1.dist-info/top_level.txt
gsam_utils-0.2.1.dist-info/RECORD
