Metadata-Version: 2.4
Name: gsam_utils
Version: 0.2.1
Summary: Private compiled utilities for GSAM workflows
Home-page: https://github.com/yebigithub/gsam_utils_repo
Author: Ye Bi
Author-email: yesbi@iastate.edu
License: Proprietary
Requires-Python: >=3.10
Dynamic: author
Dynamic: author-email
Dynamic: description
Dynamic: description-content-type
Dynamic: home-page
Dynamic: license
Dynamic: requires-python
Dynamic: summary
